{"Shader":{"ver":"0.1","info":{"id":"4dsXR4","date":"1397548314","viewed":733,"name":"fibospirals","username":"FabriceNeyret2","description":"Mouse.x to change the stippling.<br\/>","likes":2,"published":3,"flags":16,"tags":["spiral","short"],"hasliked":0},"renderpass":[{"inputs":[{"id":33,"src":"\/presets\/tex00.jpg","ctype":"keyboard","channel":2,"sampler":{"filter":"nearest","wrap":"clamp","vflip":"false","srgb":"false","internal":"byte"}}],"outputs":[{"channel":"0"}],"code":"#define PI 3.14159265359\nbool keyToggle(int ascii) \n{ return (texture2D(iChannel2,vec2((.5+float(ascii))\/256.,0.75)).x > 0.); }\n\n\nvoid mainImage( out vec4 fragColor, in vec2 fragCoord )\n{\n\tvec2 uv = 2.* (fragCoord.xy \/ iResolution.y - vec2(.8,.5));\n\tvec2 mouse = iMouse.xy \/ iResolution.xy;\n\tfloat n = mouse.x;\n\tif (iMouse.z<=0.) n = .5; \/\/ sin(.01*iGlobalTime);\n\t\n\tfloat r = length(uv); float a = atan(uv.y,uv.x); \/\/ to polar\n\t\n\tfloat k = 1.* iResolution.y\/1.5;\n\tfloat s = a -  k * r,   l,t;  \n#if 0\n\t\tuv = 1.\/1.5*(fragCoord.xy-iResolution.xy\/2.);\n\t\tr = length(uv)\/4.; a = atan(uv.y,uv.x); \n\t\ts = r - a\/(2.*PI);\n\t    t = floor(s)+a\/(2.*PI); \/\/ turns\n\t    l = PI*t*t+ 10.*iGlobalTime;\/\/ int (a\/2PI da)\n\t\ts *= 2.*PI;\n#else\t\n\t\ts = a -  k * r;\n\t\tt = floor(s\/(2.*PI)) * (2.*PI); \n\t\tl = .1*(a+k*t)*t + 10.*iGlobalTime;\n#endif\n\tfloat c = smoothstep(-1.,1.,sin(s))*smoothstep(-1.,1.,sin(10.*n*l));\n\t\n\tvec3 col;\n\tif (keyToggle(67))\n\t\tcol = vec3(sin(c));\n\telse\n\t\tcol = vec3(sin(c),sin(1.2*c),sin(1.4*c));\n\t\n\tfragColor = vec4(col,1.);\n}","name":"","description":"","type":"image"}]}}