{"Shader":{"ver":"0.1","info":{"id":"4lBGDW","date":"1428867043","viewed":798,"name":"Mic to the heart","username":"antonOTI","description":"trying the new microphone feature. I've plugged the audio into the microphone so I can experiment with whatever pass on my computer.<br\/>I don't have notion in sound so I still don't really understand how frequency differentiate from the sound wave","likes":1,"published":3,"flags":4,"tags":["noise","noob","microphone"],"hasliked":0},"renderpass":[{"inputs":[{"id":30,"src":"\/presets\/tex16.png","ctype":"texture","channel":1,"sampler":{"filter":"mipmap","wrap":"repeat","vflip":"false","srgb":"false","internal":"byte"}},{"id":32,"src":"\/presets\/mic.png","ctype":"mic","channel":0,"sampler":{"filter":"linear","wrap":"clamp","vflip":"false","srgb":"false","internal":"byte"}}],"outputs":[{"channel":"0"}],"code":"float f(vec2 a, vec2 b)\n{\n    return 1.- smoothstep(.25,.35,length((a + b) - vec2(.75, .5)));\n}\n\nvoid mainImage( out vec4 o, vec2 i )\n{\n\tvec2 u = i \/ iResolution.y;\n\tu.y += -abs(u.x - .75)*.55;\n\tvec4 n = texture2D(iChannel1,u) - .5 ;\n\tn *= texture2D(iChannel0,vec2(.45,.25)).x *.7;\n\to += vec4(f(u,n.xy), f(u,n.xz), f(u,n.zy),1);\n}","name":"","description":"","type":"image"}]}}