{"Shader":{"ver":"0.1","info":{"id":"4sjGRR","date":"1382685482","viewed":867,"name":"motion illusion","username":"FabriceNeyret2","description":"look fixly the red dot long enough, then toggle SPACE or MouseClic","likes":5,"published":3,"flags":16,"tags":["opticalillusion"],"hasliked":0},"renderpass":[{"inputs":[{"id":5,"src":"\/presets\/tex04.jpg","ctype":"texture","channel":0,"sampler":{"filter":"mipmap","wrap":"repeat","vflip":"false","srgb":"false","internal":"byte"}},{"id":33,"src":"\/presets\/tex00.jpg","ctype":"keyboard","channel":1,"sampler":{"filter":"nearest","wrap":"clamp","vflip":"false","srgb":"false","internal":"byte"}}],"outputs":[{"channel":"0"}],"code":"#define keyToggle( k)  (texture2D(iChannel1,vec2(.5+k\/256.,0.75)).x > 0.)\n\nvoid mainImage( out vec4 o, vec2 i )  {\n    vec2 R = iResolution.xy,\n\t     uv = i \/ R.y - vec2(.8,.5);\n\tfloat r = length(uv), a = atan(uv.y,uv.x), t = iGlobalTime;\n\to = vec4(0.0);\n\t\n\tif (r<.01)                                  \/\/ --- red dot \n\t\to.x++; \/\/ o = vec4(1,0,0,0);\n\telse\n\t\tif (keyToggle(32.) ||  iMouse.z > 0. )  \/\/ --- image\n\t\t\to = texture2D(iChannel0,1.-i\/R);\n\t\telse {\n\t\t\tfloat phase = 200.*r               \/\/ --- animated pattern\n\t\t\t            + 7.*( sin(uv.x*15.) + cos(uv.y*15.) + min(1.,r*10.)*sin(a*2.) );\n            o += sin(phase-26.*t);\n\t\t\t\/\/ o = vec4(max(0.,sin(phase-26.*t))); \/\/+.5*sin(4.*phase-16.*t));\n\t\t}\n\n\n}","name":"","description":"","type":"image"}]}}