{"Shader":{"ver":"0.1","info":{"id":"ld3GR4","date":"1448294808","viewed":308,"name":"Wait for it (the future is now)","username":"lenkev","description":"wait for it","likes":2,"published":3,"flags":0,"tags":["lol"],"hasliked":0},"renderpass":[{"inputs":[],"outputs":[{"channel":"0"}],"code":"float distanceTo(float x, float y, float centerX, float centerY)\n{\n    float deltaX = x - centerX;\n    float deltaY = y - centerY;\n    return sqrt(deltaX * deltaX + deltaY * deltaY);\n}\n\nvoid mainImage( out vec4 pixelColor, in vec2 pixelCoord )\n{\n    float x0 = iResolution.x\/2.0;\n    float y0 = iResolution.y\/2.0;\n    float x = pixelCoord.x;\n    float y = pixelCoord.y;\n    float PI = 3.1415;\n        \n    pixelColor = vec4(1.0, 1.0, 1.0, 1.0);\n    \n    float angle = atan(y, x) + iGlobalTime;\n    float radius = 100.0 + cos(angle*50.0)*500.0;\n    \n    if (distanceTo(x, y, x0, y0) < radius) \n    {\n        pixelColor = vec4(1.0,0.0,0.0,1.0);\n    }\n       \n}","name":"","description":"","type":"image"}]}}