{"Shader":{"ver":"0.1","info":{"id":"MlBSzR","date":"1440961967","viewed":978,"name":"Binary Glitch","username":"ddddddddd","description":"Binary Glitch - based on Luminosity. (use the Mouse to effect the strength).","likes":5,"published":3,"flags":0,"tags":["2d","binary","glitch","mirror","tile","samples","subsample"],"hasliked":0},"renderpass":[{"inputs":[{"id":36,"src":"\/presets\/vid03.webm","ctype":"video","channel":0,"sampler":{"filter":"linear","wrap":"clamp","vflip":"false","srgb":"false","internal":"byte"}}],"outputs":[{"channel":"0"}],"code":"\n\/\/ Binary Glitch - based on Luminosity.\n\/\/ use the Mouse to effect the strength.\n\n\n\/\/ by D34N 4L3X\n\/\/ dean@neuroid.co.uk\n\n\nvoid mainImage( out vec4 fragColor, in vec2 fragCoord )\n{\n\tvec2 uv = fragCoord.xy \/ iResolution.xy;\n\/\/    uv.t = 1.0 - uv.t;\n    \n    float x = uv.s;\n    float y = uv.t;\n    \n    \/\/\n    float glitchStrength = (iMouse.y + 55.55)\/iResolution.y * 5.0;\n    \n    \n    \n    \/\/ get snapped position\n    float psize = 0.04 * glitchStrength;\n    float psq = 1.0 \/ psize;\n\n    float px = floor( x * psq + 0.5) * psize;\n    float py = floor( y * psq + 0.5) * psize;\n    \n\tvec4 colSnap = texture2D( iChannel0, vec2( px,py) );\n    \n\tfloat lum = pow( 1.0 - (colSnap.r + colSnap.g + colSnap.b) \/ 3.0, glitchStrength ); \/\/ remove the minus one if you want to invert luma\n    \n    \n    \n    \/\/ do move with lum as multiplying factor\n    float qsize = psize * lum;\n    \n    float qsq = 1.0 \/ qsize;\n\n    float qx = floor( x * qsq + 0.5) * qsize;\n    float qy = floor( y * qsq + 0.5) * qsize;\n\n    float rx = (px - qx) * lum + x;\n    float ry = (py - qy) * lum + y;\n    \n\tvec4 colMove = texture2D( iChannel0, vec2( rx,ry) );\n    \n    \n    \/\/ final color\n    fragColor = colMove;\n}\n\n","name":"","description":"","type":"image"}]}}